dankmemes/__init__.py
dankmemes/ptjsonlib.py
dankmemes/ptthreads.py
dankmemes-0.0.2.dist-info/METADATA
dankmemes-0.0.2.dist-info/WHEEL
dankmemes-0.0.2.dist-info/top_level.txt
dankmemes-0.0.2.dist-info/RECORD
